divio_docs_gen/Args.py
divio_docs_gen/Section.py
divio_docs_gen/__init__.py
divio_docs_gen/__main__.py
divio_docs_gen/index.py
divio_docs_gen/markdown_parser.py
divio_docs_gen/Repo/__init__.py
divio_docs_gen/Repo/files.py
divio_docs_gen/Repo/sections.py
divio_docs_gen/write_to_disk/__init__.py
divio_docs_gen/write_to_disk/nav.py
divio_docs_gen/write_to_disk/utils.py
divio_docs_gen-0.3.0.dist-info/LICENSE
divio_docs_gen-0.3.0.dist-info/METADATA
divio_docs_gen-0.3.0.dist-info/WHEEL
divio_docs_gen-0.3.0.dist-info/entry_points.txt
divio_docs_gen-0.3.0.dist-info/top_level.txt
divio_docs_gen-0.3.0.dist-info/RECORD
