Metadata-Version: 2.1
Name: divio-docs-gen
Version: 0.3.0
Summary: Turn all the markdown files in your repos into one big, divio structrured documentation
Author-email: Denperidge <denperidge@gmail.com>
Project-URL: Homepage, https://github.com/Denperidge-Redpencil/divio-docs-gen
Project-URL: Bug Tracker, https://github.com/Denperidge-Redpencil/divio-docs-gen/issues
Classifier: Development Status :: 4 - Beta
Classifier: Environment :: Console
Classifier: Intended Audience :: Information Technology
Classifier: License :: OSI Approved :: MIT License
Classifier: Operating System :: OS Independent
Classifier: Programming Language :: Python :: 3
Classifier: Topic :: Software Development :: Documentation
Requires-Python: >=3.6
License-File: LICENSE
Requires-Dist: GitPython
Requires-Dist: python-slugify
